LICENSE
MANIFEST.in
README.rst
setup.py
subdomains/__init__.py
subdomains/middleware.py
subdomains/models.py
subdomains/utils.py
subdomains/templatetags/__init__.py
subdomains/templatetags/subdomainurls.py
subdomains/tests/__init__.py
subdomains/tests/tests.py
subdomains/tests/views.py
subdomains/tests/urls/__init__.py
subdomains/tests/urls/api.py
subdomains/tests/urls/application.py
subdomains/tests/urls/default.py
subdomains/tests/urls/marketing.py
subdomains_chiniki.egg-info/PKG-INFO
subdomains_chiniki.egg-info/SOURCES.txt
subdomains_chiniki.egg-info/dependency_links.txt
subdomains_chiniki.egg-info/not-zip-safe
subdomains_chiniki.egg-info/requires.txt
subdomains_chiniki.egg-info/top_level.txt